{
  "category": "scadaHmi",
  "libraries": [
    { "id": "scadaTags", "domains": ["scada"],
      "keywords": ["scada", "tag", "polling", "wincc", "supervisory", "اسکادا", "تگ", "پایش"] },
    { "id": "hmiDesign", "domains": ["hmi"],
      "keywords": ["hmi", "screen", "display", "operator panel", "touch", "faceplate", "اچ‌ام‌آی", "صفحه اپراتوری", "نمایشگر", "پنل لمسی"] },
    { "id": "alarms", "domains": ["scada", "hmi", "maintenance"],
      "keywords": ["alarm", "alert", "flood", "chattering", "priority", "هشدار", "آلارم", "اولویت"] },
    { "id": "historian", "domains": ["scada"],
      "keywords": ["historian", "time series", "trend", "archive", "compression", "هیستورین", "سری زمانی", "ترند", "آرشیو"] }
  ]
}
